<metadata>
  <table name="[dbo].[SpecObj]">
    <column name="[cx]">
      <summary> Cartesian X (J2000)</summary>
<quantity>pos.eq.x;pos.frame=j2000</quantity>
</column>
    <column name="[cy]">
      <summary> Cartesian Y (J2000)</summary>
<quantity>pos.eq.y;pos.frame=j2000</quantity>
</column>
    <column name="[cz]">
      <summary> Cartesian Z (J2000)</summary>
<quantity>pos.eq.z;pos.frame=j2000</quantity>
</column>
    <column name="[htmid]">
      <summary> HTM ID (J2000)</summary>
<quantity>pos.HTM; pos.eq; pos.frame=j2000</quantity>
</column>
    <column name="[zoneid]">
      <summary> Zone ID </summary>
<quantity>pos.zone</quantity>
</column>
    <column name="[Name]">
      <summary> Object name (Field-Identifier) </summary>
<quantity>meta.id;meta.main</quantity>
</column>
    <column name="[RA]">
      <summary> Right Ascension </summary>
<quantity>pos.eq.ra;pos.frame=j2000</quantity>
<unit> deg </unit>
</column>
    <column name="[DEC]">
      <summary> Degree of Declination </summary>
<quantity>pos.eq.dec;pos.frame=j2000</quantity>
<unit> deg </unit>
</column>
    <column name="[Rmag]">
      <summary> The {R} band magnitude. Filters are designated by:
Un = Identical to SDSS u' filter (both Un and SDSS u' cut at 4000 &#197; on the red side, about 200 &#197; blueward of the standard Johnson U passband)
{R} = bandpass centered at 6830 &#197; and half-power bandwidth of ~1250 &#197;
G = Same effective wavelength as the SDSS g' filter but slightly narrower. </summary>
<quantity>phot.mag;em.opt.R</quantity>
<unit> mag </unit>
</column>
    <column name="[G_R]">
      <summary> G band magnitude. Filters are designated by:
Un = Identical to SDSS u' filter (both Un and SDSS u' cut at 4000 &#197; on the red side, about 200 &#197; blueward of the standard Johnson U passband)
{R} = bandpass centered at 6830 &#197; and half-power bandwidth of ~1250 &#197;
G = Same effective wavelength as the SDSS g' filter but slightly narrower. </summary>
<quantity>phot.mag;em.opt.SDSS.g</quantity>
<unit> mag </unit>
</column>
    <column name="[U_G]">
      <summary>  U band magnitude. Filters are designated by:
Un = Identical to SDSS u' filter (both Un and SDSS u' cut at 4000 &#197; on the red side, about 200 &#197; blueward of the standard Johnson U passband)
{R} = bandpass centered at 6830 &#197; and half-power bandwidth of ~1250 &#197;
G = Same effective wavelength as the SDSS g' filter but slightly narrower. </summary>
<quantity>poht.mag;em.opt.SDSS.u</quantity>
<unit> mag </unit>
</column>
    <column name="[u_z_em]">
      <summary> Uncertainty flag on z-em </summary>
<quantity>meta.code.error;src.redshift</quantity>
</column>
    <column name="[z_em]">
      <summary> Redshift derived from emission lines. Special values of the redshift are used:
-1.000: Entries of -1.000 in the redshift column indicate that a candidate has never been attempted spectroscopically;
-2.000: in both the z-em and z-abs columns indicates that the object has been observed spectroscopically but no reliable
redshift resulted. Objects whose redshift measurement depended only on emission lines (usually Lyman &#945; only, for all but the AGN)
have a -2.000 in the z-abs column, and those objects without measurable emission lines have -2.000 in the z-em column. </summary>
<quantity>src.redshift</quantity>
</column>
    <column name="[u_z_abs]">
      <summary> Uncertainty flag on z-abs </summary>
<quantity>meta.code.error;redshift</quantity>
</column>
    <column name="[z_abs]">
      <summary> Redshift derived from absorption lines. Special values of the redshift are used:
-1.000: Entries of -1.000 in the redshift column indicate that a candidate has never been attempted spectroscopically;
-2.000: in both the z-em and z-abs columns indicates that the object has been observed spectroscopically but no reliable
redshift resulted. Objects whose redshift measurement depended only on emission lines (usually Lyman &#945; only, for all but the AGN)
have a -2.000 in the z-abs column, and those objects without measurable emission lines have -2.000 in the z-em column. </summary>
<quantity>src.redshift</quantity>
</column>
    <column name="[Type]">
      <summary> Object type </summary>
<quantity>src.class</quantity>
</column>
    <column name="[n_Name]">
      <summary> Notes on Name. Notes are marked as follows:
a =	"S96-CNN" indicates object names appearing in Steidel et al. (1996ApJ...462L..17S, [SH92] QSO 0000-263 NN in Simbad)
b =	This object is discussed in Macchetto et al. (1993ApJ...404..511M) and Giavalisco et al. (1994A&amp;A...288..103G, 1995ApJ...441L..13G)
c =	Objects discussed in Ellison et al. (2001ApJ...549..770E)
d =	This galaxy was previously known as Q0201-C6 in Pettini et al. (2001ApJ...554..981P) and in Shapley et al. (2001ApJ...562...95S)
o =	Objects observed in the near-IR are indicated with their old designations as in Shapley et al. (2001ApJ...562...95S) (for cross-referencing,
[PKS98] Q0256-000 ANN in Simbad).
e =	Object within central HDF region observed with HST; designation as published in Steidel et al. (1996AJ....112..352S);
f =	Object within central HDF WFPC-2 region; designation as published in Williams et al. (1996AJ....112.1335W);
g =	Redshift from Lowenthal et al. (1997ApJ...481..673L).
h =	For purely historical reasons, a number of objects in this field have been published under slightly different names. For such cases,
the previous designation is given in this column.
i =	This object does not satisfy the LBG color selection criteria, but is of interest because it is near Q1422+2309 on the plan of the
sky and is at close to the same redshift.
j =	Objects whose photometry satisfies our LBG selection criteria, but which have been discussed under alternative names, are indicated
in this column. "S96" refers to Steidel et al. (1996ApJ...462L..17S [SGP96] SSA 22 CNN in Simbad), and "S98" refers to Steidel et al.
(1998ApJ...492..428S, [SAD98] SSA 22a ANN&gt;, &lt;[SAD98] SSA 22a AANN in Simbad). Objects which at one time satisfied our selection criteria,
and which were spectroscopically observed, are included at the end of the table (see appendix of the paper).
k =	This object appeared as a member of the z=3.09 "spike" in Steidel et al. (1998ApJ...492..428S), called "SSA22b-D27". </summary>
<quantity>meta.note</quantity>
</column>
  </table>
  <table name="[dbo].[DeepImagingObs]">
    <column name="[cx]">
      <summary> Cartesian X (J2000)</summary>
<quantity>pos.eq.x;pos.frame=j2000</quantity>
</column>
    <column name="[cy]">
      <summary> Cartesian Y (J2000)</summary>
<quantity>pos.eq.y;pos.frame=j2000</quantity>
</column>
    <column name="[cz]">
      <summary> Cartesian Z (J2000)</summary>
<quantity>pos.eq.z;pos.frame=j2000</quantity>
</column>
    <column name="[htmid]">
      <summary> HTM ID (J2000)</summary>
<quantity>pos.HTM; pos.eq; pos.frame=j2000</quantity>
</column>
    <column name="[zoneid]">
      <summary> Zone ID </summary>
<quantity>pos.zone</quantity>
</column>
    <column name="[objID]">
      <summary> sequential ID </summary>
<quantity>meta.record</quantity>
</column>
    <column name="[Field]">
      <summary> Field name </summary>
<quantity>meta.id;obs.field</quantity>
</column>
    <column name="[RA]">
      <summary> Field center right ascension (J2000.0) </summary>
<quantity>pos.eq.ra;pos.frame=j2000;obs.field</quantity>
<unit> deg </unit>
</column>
    <column name="[DEC]">
      <summary> Field center declination (J2000.0) </summary>
<quantity>pos.eq.dec;pos.frame=j2000;obs.field</quantity>
<unit> deg </unit>
</column>
    <column name="[Filt]">
      <summary> Filter. Filters are designated by:
Un= Identical to SDSS u' filter (both Un and SDSS u' cut at 4000 &#197; on the red side, about 200 &#197; blueward of the standard Johnson
passband)
{R}= bandpass centered at 6830 &#197; and half-power bandwidth of &lt;1250 &#197;
G= Same effective wavelength as the SDSS g' filter but slightly narrower </summary>
<quantity>instr.filter</quantity>
</column>
    <column name="[Tel]">
      <summary> Telescope and date. Telescopes are designated as follows:
P200=	Palomar 5.08-m telescope
WHT=	William Herschel 4.2-m telescope
LCO=	Las Campanas Observatory du Pont 2.5-m telescope
NTT=	ESO 3.6-m New Technology Telescope
KPNO=	Kitt Peak 4-m Mayall telescope </summary>
<quantity>meta.code;instr.tel</quantity>
</column>
    <column name="[Scale]">
      <summary> Pixel scale </summary>
<quantity>instr.scale</quantity>
<unit> arcsec </unit>
</column>
    <column name="[FWHM]">
      <summary> FWHM </summary>
<quantity>spect.line.width</quantity>
<unit> arcsec </unit>
</column>
    <column name="[ExpTime]">
      <summary> Exposition time </summary>
<quantity>time.duration;obs.exposure</quantity>
<unit> s </unit>
</column>
    <column name="[Dim1]">
      <summary> Dimension </summary>
<quantity>phys.angSize</quantity>
<unit> arcmin </unit>
</column>
    <column name="[Dim2]">
      <summary> Dimension </summary>
<quantity>phys.angSize</quantity>
<unit> arcmin </unit>
</column>
    <column name="[Area]">
      <summary> Area </summary>
<quantity>phys.angSize.area</quantity>
<unit> arcmin+2 </unit>
</column>
  </table>
</metadata>